{"client":{"publicIp":"104.196.244.58","privateIp":"10.138.0.2","zone":"us-west1-a","name":"gcs-us-aws","testInfo":{"name":"gcs-us-aws","region":"us-west1-a","numberOfServers":1,"createNew":false,"cloudProvider":"GCS","targets":[{"name":"aws-us-gcs","region":"us-west-2","connections":1}],"machineType":null}},"server":{"vmInstance":{"publicIp":"52.27.164.153","privateIp":"172.31.46.151","zone":"us-west-2","name":"aws-us-gcs","testInfo":{"name":"aws-us-gcs","region":"us-west-2","numberOfServers":1,"createNew":false,"cloudProvider":"AWS","targets":[{"name":"gcs-us-aws","region":"us-west1-a","connections":1}],"machineType":null}},"listeningPort":5240,"assigned":true},"testResults":"{\t\"start\":\t{\t\t\"connected\":\t[{\t\t\t\t\"socket\":\t4,\t\t\t\t\"local_host\":\t\"10.138.0.2\",\t\t\t\t\"local_port\":\t49065,\t\t\t\t\"remote_host\":\t\"52.27.164.153\",\t\t\t\t\"remote_port\":\t5240\t\t\t}],\t\t\"version\":\t\"iperf 3.0.11\",\t\t\"system_info\":\t\"Linux gcs-us-aws 4.4.0-59-generic #80-Ubuntu SMP Fri Jan 6 17:47:47 UTC 2017 x86_64 x86_64 x86_64 GNU/Linux\\n\",\t\t\"timestamp\":\t{\t\t\t\"time\":\t\"Wed, 25 Jan 2017 15:46:21 GMT\",\t\t\t\"timesecs\":\t1485359181\t\t},\t\t\"connecting_to\":\t{\t\t\t\"host\":\t\"52.27.164.153\",\t\t\t\"port\":\t5240\t\t},\t\t\"cookie\":\t\"gcs-us-aws.1485359181.362376.10e1805\",\t\t\"test_start\":\t{\t\t\t\"protocol\":\t\"UDP\",\t\t\t\"num_streams\":\t1,\t\t\t\"blksize\":\t8192,\t\t\t\"omit\":\t0,\t\t\t\"duration\":\t10,\t\t\t\"bytes\":\t0,\t\t\t\"blocks\":\t0,\t\t\t\"reverse\":\t0\t\t}\t},\t\"intervals\":\t[{\t\t\t\"streams\":\t[{\t\t\t\t\t\"socket\":\t4,\t\t\t\t\t\"start\":\t0,\t\t\t\t\t\"end\":\t1.00007,\t\t\t\t\t\"seconds\":\t1.00007,\t\t\t\t\t\"bytes\":\t203218944,\t\t\t\t\t\"bits_per_second\":\t1.62564e+09,\t\t\t\t\t\"packets\":\t24807,\t\t\t\t\t\"omitted\":\tfalse\t\t\t\t}],\t\t\t\"sum\":\t{\t\t\t\t\"start\":\t0,\t\t\t\t\"end\":\t1.00007,\t\t\t\t\"seconds\":\t1.00007,\t\t\t\t\"bytes\":\t203218944,\t\t\t\t\"bits_per_second\":\t1.62564e+09,\t\t\t\t\"packets\":\t24807,\t\t\t\t\"omitted\":\tfalse\t\t\t}\t\t}, {\t\t\t\"streams\":\t[{\t\t\t\t\t\"socket\":\t4,\t\t\t\t\t\"start\":\t1.00007,\t\t\t\t\t\"end\":\t2.00014,\t\t\t\t\t\"seconds\":\t1.00007,\t\t\t\t\t\"bytes\":\t239173632,\t\t\t\t\t\"bits_per_second\":\t1.91326e+09,\t\t\t\t\t\"packets\":\t29196,\t\t\t\t\t\"omitted\":\tfalse\t\t\t\t}],\t\t\t\"sum\":\t{\t\t\t\t\"start\":\t1.00007,\t\t\t\t\"end\":\t2.00014,\t\t\t\t\"seconds\":\t1.00007,\t\t\t\t\"bytes\":\t239173632,\t\t\t\t\"bits_per_second\":\t1.91326e+09,\t\t\t\t\"packets\":\t29196,\t\t\t\t\"omitted\":\tfalse\t\t\t}\t\t}, {\t\t\t\"streams\":\t[{\t\t\t\t\t\"socket\":\t4,\t\t\t\t\t\"start\":\t2.00014,\t\t\t\t\t\"end\":\t3.00012,\t\t\t\t\t\"seconds\":\t0.999981,\t\t\t\t\t\"bytes\":\t239247360,\t\t\t\t\t\"bits_per_second\":\t1.91402e+09,\t\t\t\t\t\"packets\":\t29205,\t\t\t\t\t\"omitted\":\tfalse\t\t\t\t}],\t\t\t\"sum\":\t{\t\t\t\t\"start\":\t2.00014,\t\t\t\t\"end\":\t3.00012,\t\t\t\t\"seconds\":\t0.999981,\t\t\t\t\"bytes\":\t239247360,\t\t\t\t\"bits_per_second\":\t1.91402e+09,\t\t\t\t\"packets\":\t29205,\t\t\t\t\"omitted\":\tfalse\t\t\t}\t\t}, {\t\t\t\"streams\":\t[{\t\t\t\t\t\"socket\":\t4,\t\t\t\t\t\"start\":\t3.00012,\t\t\t\t\t\"end\":\t4.00009,\t\t\t\t\t\"seconds\":\t0.999968,\t\t\t\t\t\"bytes\":\t239239168,\t\t\t\t\t\"bits_per_second\":\t1.91397e+09,\t\t\t\t\t\"packets\":\t29204,\t\t\t\t\t\"omitted\":\tfalse\t\t\t\t}],\t\t\t\"sum\":\t{\t\t\t\t\"start\":\t3.00012,\t\t\t\t\"end\":\t4.00009,\t\t\t\t\"seconds\":\t0.999968,\t\t\t\t\"bytes\":\t239239168,\t\t\t\t\"bits_per_second\":\t1.91397e+09,\t\t\t\t\"packets\":\t29204,\t\t\t\t\"omitted\":\tfalse\t\t\t}\t\t}, {\t\t\t\"streams\":\t[{\t\t\t\t\t\"socket\":\t4,\t\t\t\t\t\"start\":\t4.00009,\t\t\t\t\t\"end\":\t5.00007,\t\t\t\t\t\"seconds\":\t0.999986,\t\t\t\t\t\"bytes\":\t239165440,\t\t\t\t\t\"bits_per_second\":\t1.91335e+09,\t\t\t\t\t\"packets\":\t29195,\t\t\t\t\t\"omitted\":\tfalse\t\t\t\t}],\t\t\t\"sum\":\t{\t\t\t\t\"start\":\t4.00009,\t\t\t\t\"end\":\t5.00007,\t\t\t\t\"seconds\":\t0.999986,\t\t\t\t\"bytes\":\t239165440,\t\t\t\t\"bits_per_second\":\t1.91335e+09,\t\t\t\t\"packets\":\t29195,\t\t\t\t\"omitted\":\tfalse\t\t\t}\t\t}, {\t\t\t\"streams\":\t[{\t\t\t\t\t\"socket\":\t4,\t\t\t\t\t\"start\":\t5.00007,\t\t\t\t\t\"end\":\t6.0001,\t\t\t\t\t\"seconds\":\t1.00003,\t\t\t\t\t\"bytes\":\t235061248,\t\t\t\t\t\"bits_per_second\":\t1.88044e+09,\t\t\t\t\t\"packets\":\t28694,\t\t\t\t\t\"omitted\":\tfalse\t\t\t\t}],\t\t\t\"sum\":\t{\t\t\t\t\"start\":\t5.00007,\t\t\t\t\"end\":\t6.0001,\t\t\t\t\"seconds\":\t1.00003,\t\t\t\t\"bytes\":\t235061248,\t\t\t\t\"bits_per_second\":\t1.88044e+09,\t\t\t\t\"packets\":\t28694,\t\t\t\t\"omitted\":\tfalse\t\t\t}\t\t}, {\t\t\t\"streams\":\t[{\t\t\t\t\t\"socket\":\t4,\t\t\t\t\t\"start\":\t6.0001,\t\t\t\t\t\"end\":\t7.00007,\t\t\t\t\t\"seconds\":\t0.999971,\t\t\t\t\t\"bytes\":\t232693760,\t\t\t\t\t\"bits_per_second\":\t1.8616e+09,\t\t\t\t\t\"packets\":\t28405,\t\t\t\t\t\"omitted\":\tfalse\t\t\t\t}],\t\t\t\"sum\":\t{\t\t\t\t\"start\":\t6.0001,\t\t\t\t\"end\":\t7.00007,\t\t\t\t\"seconds\":\t0.999971,\t\t\t\t\"bytes\":\t232693760,\t\t\t\t\"bits_per_second\":\t1.8616e+09,\t\t\t\t\"packets\":\t28405,\t\t\t\t\"omitted\":\tfalse\t\t\t}\t\t}, {\t\t\t\"streams\":\t[{\t\t\t\t\t\"socket\":\t4,\t\t\t\t\t\"start\":\t7.00007,\t\t\t\t\t\"end\":\t8.00007,\t\t\t\t\t\"seconds\":\t1,\t\t\t\t\t\"bytes\":\t239165440,\t\t\t\t\t\"bits_per_second\":\t1.91332e+09,\t\t\t\t\t\"packets\":\t29195,\t\t\t\t\t\"omitted\":\tfalse\t\t\t\t}],\t\t\t\"sum\":\t{\t\t\t\t\"start\":\t7.00007,\t\t\t\t\"end\":\t8.00007,\t\t\t\t\"seconds\":\t1,\t\t\t\t\"bytes\":\t239165440,\t\t\t\t\"bits_per_second\":\t1.91332e+09,\t\t\t\t\"packets\":\t29195,\t\t\t\t\"omitted\":\tfalse\t\t\t}\t\t}, {\t\t\t\"streams\":\t[{\t\t\t\t\t\"socket\":\t4,\t\t\t\t\t\"start\":\t8.00007,\t\t\t\t\t\"end\":\t9.00007,\t\t\t\t\t\"seconds\":\t1,\t\t\t\t\t\"bytes\":\t236101632,\t\t\t\t\t\"bits_per_second\":\t1888813056,\t\t\t\t\t\"packets\":\t28821,\t\t\t\t\t\"omitted\":\tfalse\t\t\t\t}],\t\t\t\"sum\":\t{\t\t\t\t\"start\":\t8.00007,\t\t\t\t\"end\":\t9.00007,\t\t\t\t\"seconds\":\t1,\t\t\t\t\"bytes\":\t236101632,\t\t\t\t\"bits_per_second\":\t1888813056,\t\t\t\t\"packets\":\t28821,\t\t\t\t\"omitted\":\tfalse\t\t\t}\t\t}, {\t\t\t\"streams\":\t[{\t\t\t\t\t\"socket\":\t4,\t\t\t\t\t\"start\":\t9.00007,\t\t\t\t\t\"end\":\t10.0002,\t\t\t\t\t\"seconds\":\t1.00009,\t\t\t\t\t\"bytes\":\t232611840,\t\t\t\t\t\"bits_per_second\":\t1.86072e+09,\t\t\t\t\t\"packets\":\t28395,\t\t\t\t\t\"omitted\":\tfalse\t\t\t\t}],\t\t\t\"sum\":\t{\t\t\t\t\"start\":\t9.00007,\t\t\t\t\"end\":\t10.0002,\t\t\t\t\"seconds\":\t1.00009,\t\t\t\t\"bytes\":\t232611840,\t\t\t\t\"bits_per_second\":\t1.86072e+09,\t\t\t\t\"packets\":\t28395,\t\t\t\t\"omitted\":\tfalse\t\t\t}\t\t}],\t\"end\":\t{\t\t\"streams\":\t[{\t\t\t\t\"udp\":\t{\t\t\t\t\t\"socket\":\t4,\t\t\t\t\t\"start\":\t0,\t\t\t\t\t\"end\":\t10.0002,\t\t\t\t\t\"seconds\":\t10.0002,\t\t\t\t\t\"bytes\":\t2335678464,\t\t\t\t\t\"bits_per_second\":\t1.86851e+09,\t\t\t\t\t\"jitter_ms\":\t0.142068,\t\t\t\t\t\"lost_packets\":\t270102,\t\t\t\t\t\"packets\":\t285007,\t\t\t\t\t\"lost_percent\":\t94.7703\t\t\t\t}\t\t\t}],\t\t\"sum\":\t{\t\t\t\"start\":\t0,\t\t\t\"end\":\t10.0002,\t\t\t\"seconds\":\t10.0002,\t\t\t\"bytes\":\t2335678464,\t\t\t\"bits_per_second\":\t1.86851e+09,\t\t\t\"jitter_ms\":\t0.142068,\t\t\t\"lost_packets\":\t270102,\t\t\t\"packets\":\t285007,\t\t\t\"lost_percent\":\t94.7703\t\t},\t\t\"cpu_utilization_percent\":\t{\t\t\t\"host_total\":\t15.949,\t\t\t\"host_user\":\t1.06555,\t\t\t\"host_system\":\t14.8783,\t\t\t\"remote_total\":\t1.73994,\t\t\t\"remote_user\":\t0,\t\t\t\"remote_system\":\t1.72394\t\t}\t}}"}