{"client":{"publicIp":"35.154.136.184","privateIp":"172.31.20.45","zone":"ap-south-1","name":"aws-mum-lr","testInfo":{"name":"aws-mum-lr","region":"ap-south-1","numberOfServers":1,"createNew":false,"cloudProvider":"AWS","targets":[{"name":"aws-cali-lr","region":"us-west-1","connections":1}],"machineType":null}},"server":{"vmInstance":{"publicIp":"52.53.226.116","privateIp":"172.31.4.216","zone":"us-west-1","name":"aws-cali-lr","testInfo":{"name":"aws-cali-lr","region":"us-west-1","numberOfServers":1,"createNew":false,"cloudProvider":"AWS","targets":[{"name":"aws-mum-lr","region":"ap-south-1","connections":1}],"machineType":null}},"listeningPort":5248,"assigned":true},"testResults":"{\t\"start\":\t{\t\t\"connected\":\t[{\t\t\t\t\"socket\":\t4,\t\t\t\t\"local_host\":\t\"172.31.20.45\",\t\t\t\t\"local_port\":\t60734,\t\t\t\t\"remote_host\":\t\"52.53.226.116\",\t\t\t\t\"remote_port\":\t5248\t\t\t}],\t\t\"version\":\t\"iperf 3.0.11\",\t\t\"system_info\":\t\"Linux ip-172-31-20-45 4.4.0-59-generic #80-Ubuntu SMP Fri Jan 6 17:47:47 UTC 2017 x86_64 x86_64 x86_64 GNU/Linux\\n\",\t\t\"timestamp\":\t{\t\t\t\"time\":\t\"Wed, 25 Jan 2017 16:09:11 GMT\",\t\t\t\"timesecs\":\t1485360551\t\t},\t\t\"connecting_to\":\t{\t\t\t\"host\":\t\"52.53.226.116\",\t\t\t\"port\":\t5248\t\t},\t\t\"cookie\":\t\"ip-172-31-20-45.1485360550.855470.29\",\t\t\"test_start\":\t{\t\t\t\"protocol\":\t\"UDP\",\t\t\t\"num_streams\":\t1,\t\t\t\"blksize\":\t8192,\t\t\t\"omit\":\t0,\t\t\t\"duration\":\t10,\t\t\t\"bytes\":\t0,\t\t\t\"blocks\":\t0,\t\t\t\"reverse\":\t0\t\t}\t},\t\"intervals\":\t[{\t\t\t\"streams\":\t[{\t\t\t\t\t\"socket\":\t4,\t\t\t\t\t\"start\":\t0,\t\t\t\t\t\"end\":\t1.00014,\t\t\t\t\t\"seconds\":\t1.00014,\t\t\t\t\t\"bytes\":\t137527296,\t\t\t\t\t\"bits_per_second\":\t1.10007e+09,\t\t\t\t\t\"packets\":\t16788,\t\t\t\t\t\"omitted\":\tfalse\t\t\t\t}],\t\t\t\"sum\":\t{\t\t\t\t\"start\":\t0,\t\t\t\t\"end\":\t1.00014,\t\t\t\t\"seconds\":\t1.00014,\t\t\t\t\"bytes\":\t137527296,\t\t\t\t\"bits_per_second\":\t1.10007e+09,\t\t\t\t\"packets\":\t16788,\t\t\t\t\"omitted\":\tfalse\t\t\t}\t\t}, {\t\t\t\"streams\":\t[{\t\t\t\t\t\"socket\":\t4,\t\t\t\t\t\"start\":\t1.00014,\t\t\t\t\t\"end\":\t2.00008,\t\t\t\t\t\"seconds\":\t0.999944,\t\t\t\t\t\"bytes\":\t134955008,\t\t\t\t\t\"bits_per_second\":\t1.0797e+09,\t\t\t\t\t\"packets\":\t16474,\t\t\t\t\t\"omitted\":\tfalse\t\t\t\t}],\t\t\t\"sum\":\t{\t\t\t\t\"start\":\t1.00014,\t\t\t\t\"end\":\t2.00008,\t\t\t\t\"seconds\":\t0.999944,\t\t\t\t\"bytes\":\t134955008,\t\t\t\t\"bits_per_second\":\t1.0797e+09,\t\t\t\t\"packets\":\t16474,\t\t\t\t\"omitted\":\tfalse\t\t\t}\t\t}, {\t\t\t\"streams\":\t[{\t\t\t\t\t\"socket\":\t4,\t\t\t\t\t\"start\":\t2.00008,\t\t\t\t\t\"end\":\t3.00001,\t\t\t\t\t\"seconds\":\t0.999928,\t\t\t\t\t\"bytes\":\t138674176,\t\t\t\t\t\"bits_per_second\":\t1.10947e+09,\t\t\t\t\t\"packets\":\t16928,\t\t\t\t\t\"omitted\":\tfalse\t\t\t\t}],\t\t\t\"sum\":\t{\t\t\t\t\"start\":\t2.00008,\t\t\t\t\"end\":\t3.00001,\t\t\t\t\"seconds\":\t0.999928,\t\t\t\t\"bytes\":\t138674176,\t\t\t\t\"bits_per_second\":\t1.10947e+09,\t\t\t\t\"packets\":\t16928,\t\t\t\t\"omitted\":\tfalse\t\t\t}\t\t}, {\t\t\t\"streams\":\t[{\t\t\t\t\t\"socket\":\t4,\t\t\t\t\t\"start\":\t3.00001,\t\t\t\t\t\"end\":\t4.00012,\t\t\t\t\t\"seconds\":\t1.00011,\t\t\t\t\t\"bytes\":\t125689856,\t\t\t\t\t\"bits_per_second\":\t1.00541e+09,\t\t\t\t\t\"packets\":\t15343,\t\t\t\t\t\"omitted\":\tfalse\t\t\t\t}],\t\t\t\"sum\":\t{\t\t\t\t\"start\":\t3.00001,\t\t\t\t\"end\":\t4.00012,\t\t\t\t\"seconds\":\t1.00011,\t\t\t\t\"bytes\":\t125689856,\t\t\t\t\"bits_per_second\":\t1.00541e+09,\t\t\t\t\"packets\":\t15343,\t\t\t\t\"omitted\":\tfalse\t\t\t}\t\t}, {\t\t\t\"streams\":\t[{\t\t\t\t\t\"socket\":\t4,\t\t\t\t\t\"start\":\t4.00012,\t\t\t\t\t\"end\":\t5.00012,\t\t\t\t\t\"seconds\":\t1,\t\t\t\t\t\"bytes\":\t131866624,\t\t\t\t\t\"bits_per_second\":\t1054932992,\t\t\t\t\t\"packets\":\t16097,\t\t\t\t\t\"omitted\":\tfalse\t\t\t\t}],\t\t\t\"sum\":\t{\t\t\t\t\"start\":\t4.00012,\t\t\t\t\"end\":\t5.00012,\t\t\t\t\"seconds\":\t1,\t\t\t\t\"bytes\":\t131866624,\t\t\t\t\"bits_per_second\":\t1054932992,\t\t\t\t\"packets\":\t16097,\t\t\t\t\"omitted\":\tfalse\t\t\t}\t\t}, {\t\t\t\"streams\":\t[{\t\t\t\t\t\"socket\":\t4,\t\t\t\t\t\"start\":\t5.00012,\t\t\t\t\t\"end\":\t6.00012,\t\t\t\t\t\"seconds\":\t0.999999,\t\t\t\t\t\"bytes\":\t102309888,\t\t\t\t\t\"bits_per_second\":\t8.1848e+08,\t\t\t\t\t\"packets\":\t12489,\t\t\t\t\t\"omitted\":\tfalse\t\t\t\t}],\t\t\t\"sum\":\t{\t\t\t\t\"start\":\t5.00012,\t\t\t\t\"end\":\t6.00012,\t\t\t\t\"seconds\":\t0.999999,\t\t\t\t\"bytes\":\t102309888,\t\t\t\t\"bits_per_second\":\t8.1848e+08,\t\t\t\t\"packets\":\t12489,\t\t\t\t\"omitted\":\tfalse\t\t\t}\t\t}, {\t\t\t\"streams\":\t[{\t\t\t\t\t\"socket\":\t4,\t\t\t\t\t\"start\":\t6.00012,\t\t\t\t\t\"end\":\t7.00015,\t\t\t\t\t\"seconds\":\t1.00003,\t\t\t\t\t\"bytes\":\t89120768,\t\t\t\t\t\"bits_per_second\":\t7.12948e+08,\t\t\t\t\t\"packets\":\t10879,\t\t\t\t\t\"omitted\":\tfalse\t\t\t\t}],\t\t\t\"sum\":\t{\t\t\t\t\"start\":\t6.00012,\t\t\t\t\"end\":\t7.00015,\t\t\t\t\"seconds\":\t1.00003,\t\t\t\t\"bytes\":\t89120768,\t\t\t\t\"bits_per_second\":\t7.12948e+08,\t\t\t\t\"packets\":\t10879,\t\t\t\t\"omitted\":\tfalse\t\t\t}\t\t}, {\t\t\t\"streams\":\t[{\t\t\t\t\t\"socket\":\t4,\t\t\t\t\t\"start\":\t7.00015,\t\t\t\t\t\"end\":\t8.00012,\t\t\t\t\t\"seconds\":\t0.999974,\t\t\t\t\t\"bytes\":\t89595904,\t\t\t\t\t\"bits_per_second\":\t7.16786e+08,\t\t\t\t\t\"packets\":\t10937,\t\t\t\t\t\"omitted\":\tfalse\t\t\t\t}],\t\t\t\"sum\":\t{\t\t\t\t\"start\":\t7.00015,\t\t\t\t\"end\":\t8.00012,\t\t\t\t\"seconds\":\t0.999974,\t\t\t\t\"bytes\":\t89595904,\t\t\t\t\"bits_per_second\":\t7.16786e+08,\t\t\t\t\"packets\":\t10937,\t\t\t\t\"omitted\":\tfalse\t\t\t}\t\t}, {\t\t\t\"streams\":\t[{\t\t\t\t\t\"socket\":\t4,\t\t\t\t\t\"start\":\t8.00012,\t\t\t\t\t\"end\":\t9.00012,\t\t\t\t\t\"seconds\":\t1,\t\t\t\t\t\"bytes\":\t90382336,\t\t\t\t\t\"bits_per_second\":\t7.23058e+08,\t\t\t\t\t\"packets\":\t11033,\t\t\t\t\t\"omitted\":\tfalse\t\t\t\t}],\t\t\t\"sum\":\t{\t\t\t\t\"start\":\t8.00012,\t\t\t\t\"end\":\t9.00012,\t\t\t\t\"seconds\":\t1,\t\t\t\t\"bytes\":\t90382336,\t\t\t\t\"bits_per_second\":\t7.23058e+08,\t\t\t\t\"packets\":\t11033,\t\t\t\t\"omitted\":\tfalse\t\t\t}\t\t}, {\t\t\t\"streams\":\t[{\t\t\t\t\t\"socket\":\t4,\t\t\t\t\t\"start\":\t9.00012,\t\t\t\t\t\"end\":\t10.0001,\t\t\t\t\t\"seconds\":\t1.00001,\t\t\t\t\t\"bytes\":\t122601472,\t\t\t\t\t\"bits_per_second\":\t9.80805e+08,\t\t\t\t\t\"packets\":\t14966,\t\t\t\t\t\"omitted\":\tfalse\t\t\t\t}],\t\t\t\"sum\":\t{\t\t\t\t\"start\":\t9.00012,\t\t\t\t\"end\":\t10.0001,\t\t\t\t\"seconds\":\t1.00001,\t\t\t\t\"bytes\":\t122601472,\t\t\t\t\"bits_per_second\":\t9.80805e+08,\t\t\t\t\"packets\":\t14966,\t\t\t\t\"omitted\":\tfalse\t\t\t}\t\t}],\t\"end\":\t{\t\t\"streams\":\t[{\t\t\t\t\"udp\":\t{\t\t\t\t\t\"socket\":\t4,\t\t\t\t\t\"start\":\t0,\t\t\t\t\t\"end\":\t10.0001,\t\t\t\t\t\"seconds\":\t10.0001,\t\t\t\t\t\"bytes\":\t1162723328,\t\t\t\t\t\"bits_per_second\":\t9.30167e+08,\t\t\t\t\t\"jitter_ms\":\t0.105045,\t\t\t\t\t\"lost_packets\":\t53415,\t\t\t\t\t\"packets\":\t141930,\t\t\t\t\t\"lost_percent\":\t37.6347\t\t\t\t}\t\t\t}],\t\t\"sum\":\t{\t\t\t\"start\":\t0,\t\t\t\"end\":\t10.0001,\t\t\t\"seconds\":\t10.0001,\t\t\t\"bytes\":\t1162723328,\t\t\t\"bits_per_second\":\t9.30167e+08,\t\t\t\"jitter_ms\":\t0.105045,\t\t\t\"lost_packets\":\t53415,\t\t\t\"packets\":\t141930,\t\t\t\"lost_percent\":\t37.6347\t\t},\t\t\"cpu_utilization_percent\":\t{\t\t\t\"host_total\":\t14.0601,\t\t\t\"host_user\":\t2.02053,\t\t\t\"host_system\":\t12.0149,\t\t\t\"remote_total\":\t4.17303,\t\t\t\"remote_user\":\t0,\t\t\t\"remote_system\":\t4.16053\t\t}\t}}"}